odoo/addons/hotel_restaurant/README.rst
odoo/addons/hotel_restaurant/__init__.py
odoo/addons/hotel_restaurant/__manifest__.py
odoo/addons/hotel_restaurant/demo/hotel_restaurant_data.xml
odoo/addons/hotel_restaurant/i18n/es.po
odoo/addons/hotel_restaurant/i18n/fr.po
odoo/addons/hotel_restaurant/i18n/fr_BE.po
odoo/addons/hotel_restaurant/i18n/hotel_restaurant.pot
odoo/addons/hotel_restaurant/i18n/it.po
odoo/addons/hotel_restaurant/i18n/pt_BR.po
odoo/addons/hotel_restaurant/i18n/sv.po
odoo/addons/hotel_restaurant/i18n/zh_CN.po
odoo/addons/hotel_restaurant/models/__init__.py
odoo/addons/hotel_restaurant/models/hotel_folio.py
odoo/addons/hotel_restaurant/models/hotel_menucard.py
odoo/addons/hotel_restaurant/models/hotel_restaurant.py
odoo/addons/hotel_restaurant/readme/CONTRIBUTORS.rst
odoo/addons/hotel_restaurant/readme/DESCRIPTION.rst
odoo/addons/hotel_restaurant/report/__init__.py
odoo/addons/hotel_restaurant/report/hotel_restaurant_report.py
odoo/addons/hotel_restaurant/report/hotel_restaurant_report.xml
odoo/addons/hotel_restaurant/security/ir.model.access.csv
odoo/addons/hotel_restaurant/static/description/icon.png
odoo/addons/hotel_restaurant/static/description/index.html
odoo/addons/hotel_restaurant/static/description/res2.png
odoo/addons/hotel_restaurant/static/description/res3.png
odoo/addons/hotel_restaurant/static/description/res4.png
odoo/addons/hotel_restaurant/static/description/res5.png
odoo/addons/hotel_restaurant/static/description/res6.png
odoo/addons/hotel_restaurant/static/description/serpent.png
odoo/addons/hotel_restaurant/static/img/Halva.jpg
odoo/addons/hotel_restaurant/static/img/Idli_sambar.jpg
odoo/addons/hotel_restaurant/static/img/appam1.jpg
odoo/addons/hotel_restaurant/static/img/bhaji_paw.jpg
odoo/addons/hotel_restaurant/static/img/chees_masala.jpg
odoo/addons/hotel_restaurant/static/img/chole.png
odoo/addons/hotel_restaurant/static/img/dosa.png
odoo/addons/hotel_restaurant/static/img/khandvi.jpg
odoo_addon_hotel_restaurant-15.0.1.0.0.29.dist-info/METADATA
odoo_addon_hotel_restaurant-15.0.1.0.0.29.dist-info/WHEEL
odoo_addon_hotel_restaurant-15.0.1.0.0.29.dist-info/top_level.txt
odoo_addon_hotel_restaurant-15.0.1.0.0.29.dist-info/RECORD
