Metadata-Version: 2.1
Name: odoo-addon-hotel_restaurant
Version: 15.0.1.0.0.29
Summary: Table booking facilities and Managing customers orders
Home-page: https://github.com/OCA/vertical-hotel
Author: Odoo Community Association (OCA), Serpent Consulting Services Pvt. Ltd., Odoo S.A.
Author-email: support@odoo-community.org
License: AGPL-3
Classifier: Programming Language :: Python
Classifier: Framework :: Odoo
Classifier: Framework :: Odoo :: 15.0
Classifier: License :: OSI Approved :: GNU Affero General Public License v3
Requires-Python: >=3.8
Requires-Dist: odoo-addon-hotel<15.1dev,>=15.0dev
Requires-Dist: odoo<15.1dev,>=15.0a
